quicsend_library.so
quicsend.libs/libcrypto-401bea5d.so.1.1.1k
quicsend.libs/libpython3.6m.so.1.0
quicsend.libs/libssl-52849bc7.so.1.1.1k
quicsend-0.13.0.dist-info/METADATA
quicsend-0.13.0.dist-info/top_level.txt
quicsend-0.13.0.dist-info/WHEEL
quicsend-0.13.0.dist-info/LICENSE
quicsend-0.13.0.dist-info/RECORD
quicsend/__init__.py
quicsend/quicsend_wrapper.py
quicsend/__pycache__/__init__.cpython-310.pyc
quicsend/__pycache__/quicsend_wrapper.cpython-310.pyc
