Metadata-Version: 2.1
Name: quicsend
Version: 0.13.0
Home-page: https://github.com/catid/quicsend
Author: Chris Taylor
Requires-Python: >=3
License-File: LICENSE
Requires-Dist: msgpack
